kp.cp38-win_amd64.pyd
kp-0.7.0.dist-info/LICENSE
kp-0.7.0.dist-info/METADATA
kp-0.7.0.dist-info/WHEEL
kp-0.7.0.dist-info/top_level.txt
kp-0.7.0.dist-info/RECORD
