Metadata-Version: 2.1
Name: kp
Version: 0.7.0
Summary: Vulkan Kompute: Blazing fast, mobile-enabled, asynchronous, and optimized for advanced GPU processing usecases.
Home-page: UNKNOWN
Author: Alejandro Saucedo
License: UNKNOWN
Platform: UNKNOWN
Requires-Dist: numpy (<2.0.0)
